holoscan_cli/__init__.py
holoscan_cli/__main__.py
holoscan_cli/common/argparse_types.py
holoscan_cli/common/artifact_sources.py
holoscan_cli/common/constants.py
holoscan_cli/common/dockerutils.py
holoscan_cli/common/enum_types.py
holoscan_cli/common/exceptions.py
holoscan_cli/common/sdk_utils.py
holoscan_cli/common/utils.py
holoscan_cli/logging.json
holoscan_cli/nics/__init__.py
holoscan_cli/nics/nics.py
holoscan_cli/package-source.json
holoscan_cli/packager/__init__.py
holoscan_cli/packager/arguments.py
holoscan_cli/packager/config_reader.py
holoscan_cli/packager/container_builder.py
holoscan_cli/packager/manifest_files.py
holoscan_cli/packager/models.py
holoscan_cli/packager/package_command.py
holoscan_cli/packager/packager.py
holoscan_cli/packager/parameters.py
holoscan_cli/packager/platforms.py
holoscan_cli/packager/templates/Dockerfile-cu12.jinja2
holoscan_cli/packager/templates/Dockerfile.jinja2
holoscan_cli/packager/templates/dockerignore
holoscan_cli/packager/templates/tools.sh
holoscan_cli/py.typed
holoscan_cli/runner/__init__.py
holoscan_cli/runner/resources.py
holoscan_cli/runner/run_command.py
holoscan_cli/runner/runner.py
holoscan_cli/version/__init__.py
holoscan_cli/version/version.py
holoscan_cli-3.10.0.dist-info/METADATA
holoscan_cli-3.10.0.dist-info/WHEEL
holoscan_cli-3.10.0.dist-info/entry_points.txt
holoscan_cli-3.10.0.dist-info/licenses/LICENSE
holoscan_cli-3.10.0.dist-info/RECORD
