Metadata-Version: 2.4
Name: holoscan-cli
Version: 3.10.0
Summary: Command line interface for packaging and running Holoscan applications.
License: Apache-2.0
License-File: LICENSE
Keywords: AI,holoscan,medical,streaming,HPC,nvidia,docker,container
Author: NVIDIA
Maintainer: mocsharp
Requires-Python: >=3.10,<3.14
Classifier: Development Status :: 5 - Production/Stable
Classifier: Environment :: Console
Classifier: Environment :: GPU :: NVIDIA CUDA :: 12
Classifier: Intended Audience :: Developers
Classifier: Intended Audience :: Education
Classifier: Intended Audience :: Healthcare Industry
Classifier: Intended Audience :: Science/Research
Classifier: License :: OSI Approved :: Apache Software License
Classifier: Operating System :: POSIX :: Linux
Classifier: Programming Language :: Python :: 3
Classifier: Programming Language :: Python :: 3.10
Classifier: Programming Language :: Python :: 3.11
Classifier: Programming Language :: Python :: 3.12
Classifier: Programming Language :: Python :: 3.13
Classifier: Topic :: Scientific/Engineering :: Artificial Intelligence
Classifier: Topic :: Software Development :: Libraries :: Python Modules
Classifier: Typing :: Typed
Requires-Dist: Jinja2 (>=3.1.6,<4.0.0)
Requires-Dist: packaging (>=25.0,<26.0)
Requires-Dist: pip (>25.1.0)
Requires-Dist: psutil (>=7.0.0,<8.0)
Requires-Dist: python-on-whales (>=0.77.0)
Requires-Dist: pyyaml (>=6.0,<7.0)
Requires-Dist: requests (>=2.32,<3.0)
Project-URL: Documentation, https://docs.nvidia.com/holoscan/sdk-user-guide/index.html
Project-URL: Homepage, https://github.com/nvidia-holoscan/holoscan-cli
Project-URL: Repository, https://github.com/nvidia-holoscan/holoscan-cli
